report_tools/__init__.py
report_tools/pdf_editor.cp37-win_amd64.pyd
report_tools/report_pdf.cp37-win_amd64.pyd
report_tools-0.1.6.dist-info/LICENSE.txt
report_tools-0.1.6.dist-info/METADATA
report_tools-0.1.6.dist-info/WHEEL
report_tools-0.1.6.dist-info/top_level.txt
report_tools-0.1.6.dist-info/RECORD
