Metadata-Version: 2.1
Name: report-tools
Version: 0.1.6
Summary: Create reports
Home-page: https://github.com/pypa/sampleproject
Author: anonymous
Author-email: anonymous@gmail.com
Project-URL: Bug Tracker, https://github.com/pypa/sampleproject/issues
Classifier: Programming Language :: Python :: 3
Classifier: License :: OSI Approved :: MIT License
Classifier: Operating System :: OS Independent
Requires-Python: >=3.6
License-File: LICENSE.txt
